pydocstyle/__init__.py
pydocstyle/__main__.py
pydocstyle/_version.py
pydocstyle/checker.py
pydocstyle/cli.py
pydocstyle/config.py
pydocstyle/data/imperatives.txt
pydocstyle/data/imperatives_blacklist.txt
pydocstyle/parser.py
pydocstyle/utils.py
pydocstyle/violations.py
pydocstyle/wordlists.py
pydocstyle-6.2.1.dist-info/entry_points.txt
pydocstyle-6.2.1.dist-info/METADATA
pydocstyle-6.2.1.dist-info/WHEEL
pydocstyle-6.2.1.dist-info/RECORD
