Metadata-Version: 2.1
Name: pydocstyle
Version: 6.2.1
Summary: Python docstring style checker
Home-page: https://www.pydocstyle.org/en/stable/
License: MIT
Author: Amir Rachum
Author-email: amir@rachum.com
Requires-Python: >=3.6
Classifier: Development Status :: 5 - Production/Stable
Classifier: Environment :: Console
Classifier: Intended Audience :: Developers
Classifier: License :: OSI Approved :: MIT License
Classifier: Operating System :: OS Independent
Classifier: Programming Language :: Python :: 3
Classifier: Programming Language :: Python :: 3.6
Classifier: Programming Language :: Python :: 3.7
Classifier: Programming Language :: Python :: 3.8
Classifier: Programming Language :: Python :: 3.9
Classifier: Programming Language :: Python :: 3.10
Classifier: Programming Language :: Python :: 3.11
Provides-Extra: toml
Requires-Dist: importlib-metadata (>=2.0.0,<5.0.0) ; python_version < "3.8"
Requires-Dist: snowballstemmer (>=2.2.0)
Requires-Dist: tomli (>=1.2.3) ; (python_version < "3.11") and (extra == "toml")
Project-URL: Documentation, https://www.pydocstyle.org/en/stable/
Project-URL: Repository, https://github.com/PyCQA/pydocstyle
Project-URL: Release Notes, https://www.pydocstyle.org/en/stable/release_notes.html
